AmitMeltzer/__init__.py
AmitMeltzer/main.py
AmitMeltzer/pacman.py
AmitMeltzer/simonsays.py
AmitMeltzer/test.py
AmitMeltzer-0.1.5.dist-info/METADATA
AmitMeltzer-0.1.5.dist-info/WHEEL
AmitMeltzer-0.1.5.dist-info/top_level.txt
AmitMeltzer-0.1.5.dist-info/RECORD
