Metadata-Version: 2.1
Name: AmitMeltzer
Version: 0.1.5
Summary: A python Module for my girlfriend :)
Home-page: https://github.com/eilonlif
Author: Eilon Lifshitz
Author-email: eilonlif@gmail.com
Classifier: Programming Language :: Python :: 3
Classifier: License :: OSI Approved :: MIT License
Classifier: Operating System :: OS Independent
